README.md
setup.py
selfstoredict/__init__.py
selfstoredict/selfstoredict.py
selfstoredict.egg-info/PKG-INFO
selfstoredict.egg-info/SOURCES.txt
selfstoredict.egg-info/dependency_links.txt
selfstoredict.egg-info/top_level.txt