Metadata-Version: 1.0
Name: selfstoredict
Version: 0.10
Summary: a python class delivering a dict that stores itself into a JSON file or a redis db
Home-page: https://github.com/markus61/selfstoredict
Author: markus
Author-email: ms@dom.de
License: MIT
Platform: UNKNOWN
